<metadata>
	<idinfo>
		<citation>
			<citeinfo>
				<origin>Russia (Federation). General'nyi shtab. Voenno-topograficheskoe upravlenie</origin>
				<pubdate>1974</pubdate>
				<title>Kitai provintsiia Shan'si. Taiiuan' (J-49-69, 70, 81, 82). Sheet 2</title>
				<edition>2002 [electronic data]</edition>
				<geoform>remote-sensing image</geoform>
				<pubinfo>
					<pubplace>Moscow</pubplace>
					<publish>East View Cartographic</publish>
				</pubinfo>
				<othercit>Title from disc: Taiyuan. At head of title: China 1:25,000 Russian city plan. Gauss-Krugger/Pulkovo 1942/Krassovsky projection. 1 computer optical disc, 4 3/4 in. Raster format. Format: Tiff.</othercit>
				<onlink>http://gisserver.princeton.edu/map/680</onlink>
			</citeinfo>
		</citation>
		<descript>
			<abstract>This is a map of the city of Taiyuan, China shown at a 1:25,000 scale. This is a Russian map purchased from East View Cartographic.</abstract>
			<purpose>The purpose is to view the map in digital format.</purpose>
		</descript>
		<timeperd>
			<timeinfo>
				<sngdate>
					<caldate>1974</caldate>
				</sngdate>
			</timeinfo>
			<current>publication date</current>
		</timeperd>
		<status>
			<progress>Complete</progress>
			<update>As needed</update>
		</status>
		<spdom>
			<bounding>
				<westbc>112.4243</westbc>
				<eastbc>112.643</eastbc>
				<northbc>37.8543</northbc>
				<southbc>37.7289</southbc>
			</bounding>
		</spdom>
		<keywords>
			<theme>
				<themekt>None</themekt>
				<themekey>Roads</themekey>
				<themekey>Railroads</themekey>
				<themekey>Transportation</themekey>
				<themekey>Industry</themekey>
				<themekey>City map</themekey>
				<themekey>Facilities and Structures</themekey>
			</theme>
			<place>
				<placekt>None</placekt>
				<placekey>Taiyuan</placekey>
				<placekey>Shaanxi</placekey>
				<placekey>Shaanxi Sheng</placekey>
				<placekey>Taiiuan</placekey>
				<placekey>China</placekey>
				<placekey>G7824.T3C2.1974.E3C3</placekey>
			</place>
		</keywords>
		<accconst>No restriction</accconst>
		<useconst>No restriction</useconst>
		<ptcontac>
			<cntinfo>
				<cntorgp>
					<cntorg>Princeton University</cntorg>
					<cntper>Tsering Wangyal Shawa</cntper>
				</cntorgp>
				<cntpos>GIS Librarian</cntpos>
				<cntaddr>
					<addrtype>mailing</addrtype>
				</cntaddr>
				<cntvoice>609-258-6804</cntvoice>
				<cntemail>shawatw@princeton.edu</cntemail>
				<hours>8:45 am - 5:00 pm</hours>
			</cntinfo>
		</ptcontac>
		<secinfo>
			<secclass>Unclassified</secclass>
		</secinfo>
		<native>Microsoft Windows 2000 Version 5.0 (Build 2195) Service Pack 2; ESRI ArcCatalog 8.3.0.800</native>
	</idinfo>
	<dataqual>
		<lineage>
			<procstep>
				<procdesc>Scanned map purchased from East View Cartographic. Scanned at 400 dpi according to East View Cartographic. The files were originally in the TIFF format, and were compressed by the Mapping Science GeoJP2 software version 1.04.02. The compression ratio was 10:1.</procdesc>
			</procstep>
		</lineage>
	</dataqual>
	<spref>
		<horizsys>
			<geograph>
				<geogunit>Decimal degrees</geogunit>
			</geograph>
		</horizsys>
	</spref>
	<distinfo>
		<distrib>
			<cntinfo>
				<cntperp>
					<cntper>Tsering Wangyal Shawa</cntper>
					<cntorg>Princeton University</cntorg>
				</cntperp>
				<cntpos>GIS Librarian</cntpos>
				<cntaddr>
					<addrtype>mailing</addrtype>
				</cntaddr>
				<cntvoice>609-258-6804</cntvoice>
				<cntemail>shawatw@princeton.edu</cntemail>
				<hours>8:45 am - 5:00 pm</hours>
			</cntinfo>
		</distrib>
		<resdesc>Static Map Images</resdesc>
	</distinfo>
	<metainfo>
		<metd>20040611</metd>
		<metc>
			<cntinfo>
				<cntorgp>
					<cntorg>Princeton University</cntorg>
					<cntper>Tsering Wangyal Shawa</cntper>
				</cntorgp>
				<cntpos>GIS Librarian</cntpos>
				<cntaddr>
					<addrtype>mailing address</addrtype>
					<city>Princeton</city>
					<state>NJ</state>
					<postal>08544</postal>
				</cntaddr>
				<cntvoice>609-258-6804</cntvoice>
				<cntemail>shawatw@princeton.edu</cntemail>
				<hours>8:45 am - 5:00 pm</hours>
			</cntinfo>
		</metc>
		<metstdn>FGDC Content Standards for Digital Geospatial Metadata</metstdn>
		<metstdv>FGDC-STD-001-1998</metstdv>
		<mettc>local time</mettc>
		<metextns>
			<metprof>ESRI Metadata Profile</metprof>
		</metextns>
	</metainfo>
<Esri><PublishedDocID>{EDB42FF2-D4D4-43F5-B417-2D3E5E6AEF90}</PublishedDocID><PublishStatus>Published</PublishStatus></Esri><mdFileID>{EDB42FF2-D4D4-43F5-B417-2D3E5E6AEF90}</mdFileID></metadata>