<metadata>
  <idinfo>
    <citation>
      <citeinfo>
        <origin>Boundary Solutions, Inc.</origin>
        <pubdate>20070401</pubdate>
        <title>Bronx County (The Bronx), New York land parcels, 2007</title>
        <geoform>vector digital data</geoform>
        <onlink>http://map.princeton.edu/data/f7/62/3f/28/d/content/restricted/data.zip</onlink>
      </citeinfo>
    </citation>
    <descript>
      <abstract>Land parcels in Bronx County (The Bronx), New York, 2007.</abstract>
      <purpose>For use with GIS software.</purpose>
    </descript>
    <timeperd>
      <timeinfo>
        <sngdate>
          <caldate>20070401</caldate>
        </sngdate>
      </timeinfo>
      <current>Version date.</current>
    </timeperd>
    <status>
      <progress>Complete</progress>
      <update>Unknown</update>
    </status>
    <spdom>
      <bounding>
        <westbc>-73.933616</westbc>
        <eastbc>-73.765287</eastbc>
        <northbc>40.915474</northbc>
        <southbc>40.785335</southbc>
      </bounding>
    </spdom>
    <keywords>
      <theme>
        <themekt>None</themekt>
        <themekey>parcels</themekey>
        <themekey>tax parcels</themekey>
        <themekey>land use</themekey>
        <themekey>value</themekey>
        <themekey>ownership</themekey>
        <themekey>property maps</themekey>
        <themekey>cadastral maps</themekey>
        <themekey>land value</themekey>
        <themekey>property</themekey>
        <themekey>parcel</themekey>
      </theme>
      <theme>
        <themekt>ISO 19115 Topic Categories</themekt>
        <themekey>planningCadastre</themekey>
      </theme>
      <place>
        <placekt>None</placekt>
        <placekey>Bronx</placekey>
        <placekey>New York</placekey>
        <placekey>New York City</placekey>
        <placekey>Bronx County</placekey>
      </place>
    </keywords>
    <accconst>None</accconst>
    <useconst>Data are licensed to Princeton University-affiliated persons only.</useconst>
    <ptcontac>
      <cntinfo>
        <cntorgp>
          <cntorg>Map and Geospatial Information Center, Lewis Library, Princeton University</cntorg>
        </cntorgp>
        <cntaddr>
          <addrtype>mailing and physical</addrtype>
          <address>Map and Geospatial Information Center, Lewis Library, Princeton University</address>
          <city>Princeton</city>
          <state>NJ</state>
          <postal>08544</postal>
          <country>US</country>
        </cntaddr>
        <cntvoice>609-258-1097</cntvoice>
      </cntinfo>
    </ptcontac>
    <datacred>National ParcelMap Data Portal</datacred>
    <native>Microsoft Windows 7 Version 6.1 (Build 7601) Service Pack 1; Esri ArcGIS 10.2.0.3348</native>
  </idinfo>
  <spdoinfo>
    <direct>Vector</direct>
    <ptvctinf>
      <sdtsterm>
        <sdtstype>GT-polygon composed of chains</sdtstype>
        <ptvctcnt>88912</ptvctcnt>
      </sdtsterm>
    </ptvctinf>
  </spdoinfo>
  <spref>
    <horizsys>
      <geograph>
        <latres>8.9831528411952133e-009</latres>
        <longres>8.9831528411952133e-009</longres>
        <geogunit>Decimal Degrees</geogunit>
      </geograph>
      <geodetic>
        <horizdn>D North American 1983</horizdn>
        <ellips>GRS 1980</ellips>
        <semiaxis>6378137.0</semiaxis>
        <denflat>298.257222101</denflat>
      </geodetic>
    </horizsys>
  </spref>
  <eainfo>
    <detailed>
      <enttyp>
        <enttypl>parcel_36005</enttypl>
      </enttyp>
      <attr>
        <attrlabl>YCOORD</attrlabl>
        <attrdef>Latitude of point-in-parcel.</attrdef>
        <attrdefs>NPDP Standard Extended Attribute Table Format</attrdefs>
      </attr>
      <attr>
        <attrlabl>OWNER</attrlabl>
        <attrdef>Owner name.</attrdef>
        <attrdefs>NPDP Standard Extended Attribute Table Format</attrdefs>
      </attr>
      <attr>
        <attrlabl>XCOORD</attrlabl>
        <attrdef>Longitude of point-in-parcel.</attrdef>
        <attrdefs>NPDP Standard Extended Attribute Table Format</attrdefs>
      </attr>
      <attr>
        <attrlabl>LAND_VALUE</attrlabl>
        <attrdef>Assessed land value.</attrdef>
        <attrdefs>NPDP Standard Extended Attribute Table Format</attrdefs>
      </attr>
      <attr>
        <attrlabl>STD_LAND_U</attrlabl>
        <attrdef>Standardized land use code.</attrdef>
        <attrdefs>NPDP Standard Extended Attribute Table Format</attrdefs>
        <attrdomv>
          <edom>
            <edomv>10</edomv>
            <edomvd>Parking Facilities</edomvd>
          </edom>
          <edom>
            <edomv>06</edomv>
            <edomvd>Industrial and Manufacturing</edomvd>
          </edom>
          <edom>
            <edomv>05</edomv>
            <edomvd>Commercial and Office Buildings</edomvd>
          </edom>
          <edom>
            <edomv>04</edomv>
            <edomvd>Mixed Residential and Commercial Buildings</edomvd>
          </edom>
          <edom>
            <edomv>03</edomv>
            <edomvd>Multi Family Elevator Buildings</edomvd>
          </edom>
          <edom>
            <edomv>08</edomv>
            <edomvd>Public Facilities and Institutions</edomvd>
          </edom>
          <edom>
            <edomv>07</edomv>
            <edomvd>Transportation and Utility</edomvd>
          </edom>
          <edom>
            <edomv>02</edomv>
            <edomvd>Multi Family Walk Up Buldings</edomvd>
          </edom>
          <edom>
            <edomv>09</edomv>
            <edomvd>Open Space and Outdoor Recreation</edomvd>
          </edom>
          <edom>
            <edomv>11</edomv>
            <edomvd>Vacant Land</edomvd>
          </edom>
          <edom>
            <edomv>01</edomv>
            <edomvd>One &amp; Two Family Buildings</edomvd>
          </edom>
        </attrdomv>
      </attr>
      <attr>
        <attrlabl>MAXY</attrlabl>
        <attrdef>Longitude of upper right parcel bounding box.</attrdef>
        <attrdefs>NPDP Standard Extended Attribute Table Format</attrdefs>
      </attr>
      <attr>
        <attrlabl>MINX</attrlabl>
        <attrdef>Longitude of lower left parcel bounding box.</attrdef>
        <attrdefs>NPDP Standard Extended Attribute Table Format</attrdefs>
      </attr>
      <attr>
        <attrlabl>SIT_FULL_S</attrlabl>
        <attrdef>Full street address.</attrdef>
        <attrdefs>NPDP Standard Extended Attribute Table Format</attrdefs>
      </attr>
      <attr>
        <attrlabl>FIPS</attrlabl>
        <attrdef>Unique number assigned to county by Census.</attrdef>
        <attrdefs>NPDP Standard Extended Attribute Table Format</attrdefs>
      </attr>
      <attr>
        <attrlabl>APN</attrlabl>
        <attrdef>Assessors Parcel Number.</attrdef>
        <attrdefs>NPDP Standard Extended Attribute Table Format</attrdefs>
      </attr>
      <attr>
        <attrlabl>STATE</attrlabl>
        <attrdef>State.</attrdef>
        <attrdefs>NPDP Standard Extended Attribute Table Format</attrdefs>
      </attr>
      <attr>
        <attrlabl>LOT_SIZE</attrlabl>
        <attrdef>Lot size or area.</attrdef>
        <attrdefs>NPDP Standard Extended Attribute Table Format</attrdefs>
      </attr>
      <attr>
        <attrlabl>COUNTY</attrlabl>
        <attrdef>County name.</attrdef>
        <attrdefs>NPDP Standard Extended Attribute Table Format</attrdefs>
      </attr>
      <attr>
        <attrlabl>FID</attrlabl>
        <attrdef>Internal feature number.</attrdef>
        <attrdefs>Esri</attrdefs>
        <attrdomv>
          <udom>Sequential unique whole numbers that are automatically generated.</udom>
        </attrdomv>
      </attr>
      <attr>
        <attrlabl>SIT_ZIP</attrlabl>
        <attrdef>Situs ZIP Code.</attrdef>
        <attrdefs>NPDP Standard Extended Attribute Table Format</attrdefs>
      </attr>
      <attr>
        <attrlabl>Shape</attrlabl>
        <attrdef>Feature geometry.</attrdef>
        <attrdefs>Esri</attrdefs>
        <attrdomv>
          <udom>Coordinates defining the features.</udom>
        </attrdomv>
      </attr>
      <attr>
        <attrlabl>MAXX</attrlabl>
        <attrdef>Longitude of upper right parcel bounding box.</attrdef>
        <attrdefs>NPDP Standard Extended Attribute Table Format</attrdefs>
      </attr>
      <attr>
        <attrlabl>TOT_VALUE</attrlabl>
        <attrdef>Total assessed value.</attrdef>
        <attrdefs>NPDP Standard Extended Attribute Table Format</attrdefs>
      </attr>
      <attr>
        <attrlabl>MINY</attrlabl>
        <attrdef>Latitude of lower left parcel bounding box.</attrdef>
        <attrdefs>NPDP Standard Extended Attribute Table Format</attrdefs>
      </attr>
    </detailed>
  </eainfo>
  <distinfo>
    <resdesc>Downloadable Data</resdesc>
  </distinfo>
  <metainfo>
    <metd>20140806</metd>
    <metc>
      <cntinfo>
        <cntorgp>
          <cntorg>Map and Geospatial Information Center, Lewis Library, Princeton University</cntorg>
        </cntorgp>
        <cntaddr>
          <addrtype>mailing and physical</addrtype>
          <address>Map and Geospatial Information Center, Lewis Library, Princeton University</address>
          <city>Princeton</city>
          <state>NJ</state>
          <postal>08544</postal>
          <country>US</country>
        </cntaddr>
        <cntvoice>609-258-1097</cntvoice>
      </cntinfo>
    </metc>
    <metstdn>FGDC Content Standard for Digital Geospatial Metadata</metstdn>
    <metstdv>FGDC-STD-001-1998</metstdv>
    <mettc>local time</mettc>
    <metuc>Data are licensed to Princeton University-affiliated persons only.</metuc>
    <metsi>
      <metsc>Unclassified</metsc>
    </metsi>
  </metainfo>
</metadata>